periodparser/__init__.py
periodparser/dict/__init__.py
periodparser/dict/keywords.py
periodparser/dict/morph.py
periodparser/dict/time_words.txt
periodparser/models/__init__.py
periodparser/models/abstract_period.py
periodparser/models/dates_raw_data.py
periodparser/models/i_has_edges.py
periodparser/models/parse_result.py
periodparser/models/parser_models.py
periodparser/models/text_token.py
periodparser/recognizers/__init__.py
periodparser/recognizers/dates_period_recognizer.py
periodparser/recognizers/day_of_week_recognizer.py
periodparser/recognizers/days_month_recognizer.py
periodparser/recognizers/holidays_recognizer.py
periodparser/recognizers/month_recognizer.py
periodparser/recognizers/part_of_day_recognizer.py
periodparser/recognizers/recognizer.py
periodparser/recognizers/relative_date_recognizer.py
periodparser/recognizers/relative_day_recognizer.py
periodparser/recognizers/time_recognizer.py
periodparser/recognizers/time_span_recognizer.py
periodparser/recognizers/year_recognizer.py
periodparser/sugar.py
periodparser/text_parser.py
periodparser/utils/__init__.py
periodparser/utils/helpers.py
periodparser/utils/parser_extractors.py
periodparser/utils/parser_utils.py
periodparser-1.0.4.dist-info/METADATA
periodparser-1.0.4.dist-info/WHEEL
periodparser-1.0.4.dist-info/RECORD
