Metadata-Version: 2.1
Name: periodparser
Version: 1.0.4
Summary: python parser for human readable period dates
Home-page: https://github.com/fennr/periodparser
Author: fenn_r
Author-email: fenrir1121@gmail.com
Requires-Python: >=3.8,<4.0
Classifier: Programming Language :: Python :: 3
Classifier: Programming Language :: Python :: 3.8
Classifier: Programming Language :: Python :: 3.9
Classifier: Programming Language :: Python :: 3.10
Classifier: Programming Language :: Python :: 3.11
Project-URL: Repository, https://github.com/fennr/periodparser
